docs/Makefile
docs/__init__.py
docs/conf.py
docs/index.rst
docs/make.bat
magen_id_client-2.1a0.dist-info/DESCRIPTION.rst
magen_id_client-2.1a0.dist-info/METADATA
magen_id_client-2.1a0.dist-info/RECORD
magen_id_client-2.1a0.dist-info/WHEEL
magen_id_client-2.1a0.dist-info/metadata.json
magen_id_client-2.1a0.dist-info/top_level.txt
magen_id_client_apis/__init__.py
magen_id_client_apis/magen_client.py
magen_id_client_apis/magen_client_handler.py
magen_id_client_apis/utilities.py
