Metadata-Version: 2.0
Name: magen-id-client
Version: 2.1a0
Summary: Magen ID Client Package
Home-page: UNKNOWN
Author: Mizanul Chowdhury
Author-email: michowdh@cisco.com
License: UNKNOWN
Platform: UNKNOWN
Classifier: Development Status :: 2 - Pre-Alpha
Classifier: Intended Audience :: Education
Classifier: Intended Audience :: Financial and Insurance Industry
Classifier: Intended Audience :: Healthcare Industry
Classifier: Intended Audience :: Legal Industry
Classifier: Topic :: Security
Classifier: License :: Other/Proprietary License
Classifier: Programming Language :: Python :: 3.5
Requires-Dist: flake8 (>=3.2.1)
Requires-Dist: pytest (>=3.0.2)
Requires-Dist: requests (>=2.13.0)
Requires-Dist: responses (>=0.8.1)
Requires-Dist: Sphinx (>=1.5.1)
Requires-Dist: wheel (>=0.30.0a0)
Requires-Dist: magen-rest-service (>=1.1a)
